[{"id":"234370","name":"風の声を聴きながら / コラージュ","type":3,"ratingTotal":54,"ratingScore":7.4,"tags":{},"RelationScore":"1.923076923076923E-02"},{"id":"4581","name":"悲しみに負けないで / KOHAKU","type":3,"ratingTotal":27,"ratingScore":8.3,"tags":{},"RelationScore":"1.923076923076923E-02"},{"id":"61426","name":"あなたの知らない看護婦～性的病棟24時～","type":2,"ratingTotal":142,"ratingScore":6.4,"tags":{},"RelationScore":"1.923076923076923E-02"},{"id":"135464","name":"あなたに花を捧げましょう","type":1,"ratingTotal":1,"ratingScore":5,"tags":{},"RelationScore":"1.923076923076923E-02"},{"id":"247398","name":"神達に拾われた男  (1)","type":1,"ratingTotal":0,"ratingScore":0,"tags":{},"RelationScore":"1.923076923076923E-02"},{"id":"69176","name":"星屑ニーナ","type":1,"ratingTotal":142,"ratingScore":8.1,"tags":{},"RelationScore":"1.5384615384615385E-02"},{"id":"63980","name":"あつまれ!  学園天国","type":1,"ratingTotal":1,"ratingScore":5,"tags":{},"RelationScore":"1.5384615384615385E-02"},{"id":"1604","name":"テイルズ オブ ジ アビス","type":4,"ratingTotal":171,"ratingScore":8.3,"tags":{},"RelationScore":"1.5384615384615385E-02"},{"id":"26259","name":"あなただけ見つめてる","type":3,"ratingTotal":65,"ratingScore":8.7,"tags":{},"RelationScore":"1.5384615384615385E-02"},{"id":"198734","name":"あなたに恋する恋愛ルセット","type":4,"ratingTotal":168,"ratingScore":6.4,"tags":{},"RelationScore":"1.5384615384615385E-02"}]