[{"id":"47998","name":"10歳の保健体育","type":1,"ratingTotal":13,"ratingScore":7.1,"tags":{},"RelationScore":"8E-02"},{"id":"10384","name":"30歳の保健体育","type":2,"ratingTotal":935,"ratingScore":6.5,"tags":{},"RelationScore":"7E-02"},{"id":"91223","name":"16:00の召喚魔法 1","type":1,"ratingTotal":0,"ratingScore":0,"tags":{},"RelationScore":"4.166666666666666E-02"},{"id":"111689","name":"妹と保健体育","type":4,"ratingTotal":56,"ratingScore":4.7,"tags":{},"RelationScore":"4E-02"},{"id":"281916","name":"15歳のテロリスト","type":1,"ratingTotal":6,"ratingScore":7.3,"tags":{},"RelationScore":"3.0000000000000006E-02"},{"id":"35518","name":"棺姫のチャイカ 1","type":1,"ratingTotal":14,"ratingScore":7,"tags":{},"RelationScore":"3.0000000000000006E-02"},{"id":"156921","name":"魔女の絶対道徳 1","type":1,"ratingTotal":2,"ratingScore":7,"tags":{"NOCO":1,"森田季節":1,"轻小说":1},"RelationScore":"3.0000000000000006E-02"},{"id":"77757","name":"14 to 1","type":3,"ratingTotal":35,"ratingScore":7.1,"tags":{},"RelationScore":"3.0000000000000006E-02"},{"id":"1277","name":"灼眼のシャナ 1","type":1,"ratingTotal":53,"ratingScore":7.6,"tags":{},"RelationScore":"3.0000000000000006E-02"},{"id":"8683","name":"扉の外 1","type":1,"ratingTotal":23,"ratingScore":7.5,"tags":{},"RelationScore":"3.0000000000000006E-02"}]