[{"id":"161662","name":"アマカノ","type":2,"ratingTotal":227,"ratingScore":6.4,"tags":{},"RelationScore":"1E-01"},{"id":"295350","name":"アマカノ2","type":4,"ratingTotal":70,"ratingScore":8,"tags":{},"RelationScore":"8E-02"},{"id":"189289","name":"アマカノ+","type":4,"ratingTotal":34,"ratingScore":7.9,"tags":{},"RelationScore":"8E-02"},{"id":"134673","name":"アカギ","type":6,"ratingTotal":68,"ratingScore":7.5,"tags":{},"RelationScore":"5E-02"},{"id":"133644","name":"マジカノ","type":1,"ratingTotal":3,"ratingScore":6.7,"tags":{},"RelationScore":"5E-02"},{"id":"196964","name":"アイカギ","type":4,"ratingTotal":243,"ratingScore":6.3,"tags":{},"RelationScore":"5E-02"},{"id":"56263","name":"アルカノイド","type":4,"ratingTotal":48,"ratingScore":6.3,"tags":{},"RelationScore":"5E-02"},{"id":"113947","name":"うそカノ","type":1,"ratingTotal":21,"ratingScore":7,"tags":{},"RelationScore":"5E-02"},{"id":"172310","name":"アルカナ","type":1,"ratingTotal":5,"ratingScore":6.2,"tags":{"漫画":1,"小手川ゆあ":1},"RelationScore":"5E-02"},{"id":"13210","name":"アマガミ","type":4,"ratingTotal":209,"ratingScore":7.7,"tags":{},"RelationScore":"5E-02"}]