[{"id":"166258","name":"箱庭ロワイヤル","type":1,"ratingTotal":1,"ratingScore":6,"tags":{"少女":1,"漫画":1},"RelationScore":"6.25E-02"},{"id":"25239","name":"怪盗ロワイヤル","type":6,"ratingTotal":21,"ratingScore":6,"tags":{},"RelationScore":"6.25E-02"},{"id":"193970","name":"干支✿ロワイヤル","type":1,"ratingTotal":4,"ratingScore":5.8,"tags":{},"RelationScore":"6.25E-02"},{"id":"308573","name":"恋愛×ロワイアル","type":4,"ratingTotal":26,"ratingScore":7,"tags":{},"RelationScore":"5E-02"},{"id":"108665","name":"くろのロワイヤル おはよう","type":1,"ratingTotal":7,"ratingScore":5.7,"tags":{},"RelationScore":"4.6153846153846156E-02"},{"id":"23182","name":"バトル・ロワイアル","type":1,"ratingTotal":59,"ratingScore":7.4,"tags":{},"RelationScore":"4.4444444444444446E-02"},{"id":"73722","name":"バトル・ロワイアル","type":6,"ratingTotal":111,"ratingScore":7,"tags":{},"RelationScore":"4.4444444444444446E-02"},{"id":"214122","name":"おとぎ話バトルロワイヤル","type":1,"ratingTotal":13,"ratingScore":6.2,"tags":{},"RelationScore":"4.166666666666666E-02"},{"id":"170657","name":"ゆめの底","type":1,"ratingTotal":3,"ratingScore":7,"tags":{},"RelationScore":"3.75E-02"},{"id":"6590","name":"きら星ダイヤル","type":1,"ratingTotal":21,"ratingScore":7.5,"tags":{},"RelationScore":"3.75E-02"}]