[{"id":"202485","name":"イミテーションゴールド","type":1,"ratingTotal":0,"ratingScore":0,"tags":{},"RelationScore":"3.4782608695652174E-02"},{"id":"22100","name":"トレインヒーロー","type":2,"ratingTotal":150,"ratingScore":2.1,"tags":{},"RelationScore":"3.0434782608695653E-02"},{"id":"223244","name":"ハイリスクミッションセラピー","type":1,"ratingTotal":24,"ratingScore":5.7,"tags":{},"RelationScore":"3.0434782608695653E-02"},{"id":"122896","name":"スイート マジック シンドローム","type":1,"ratingTotal":2,"ratingScore":8.5,"tags":{},"RelationScore":"3.0434782608695653E-02"},{"id":"35496","name":"プロジェクト クロスゾーン","type":4,"ratingTotal":28,"ratingScore":6.3,"tags":{},"RelationScore":"3.0434782608695653E-02"},{"id":"289471","name":"ウルトラギャラクシーファイト ニュージェネレーションヒーローズ","type":6,"ratingTotal":24,"ratingScore":6.3,"tags":{},"RelationScore":"2.9032258064516127E-02"},{"id":"224503","name":"マイホームヒーロー","type":1,"ratingTotal":168,"ratingScore":8,"tags":{},"RelationScore":"2.6086956521739136E-02"},{"id":"176284","name":"神姫プロジェクト","type":4,"ratingTotal":29,"ratingScore":5.9,"tags":{},"RelationScore":"2.6086956521739136E-02"},{"id":"307803","name":"青春ヘビーローテーション","type":1,"ratingTotal":0,"ratingScore":0,"tags":{"漫画系列":1,"少女":1},"RelationScore":"2.6086956521739136E-02"},{"id":"8380","name":"プロジェクトA子","type":2,"ratingTotal":46,"ratingScore":6.7,"tags":{},"RelationScore":"2.6086956521739136E-02"}]