[{"id":"250802","name":"人外さんの嫁","type":2,"ratingTotal":210,"ratingScore":5.3,"tags":{},"RelationScore":"3.75E-02"},{"id":"230961","name":"飛野さんのバカ","type":1,"ratingTotal":46,"ratingScore":7.4,"tags":{},"RelationScore":"3.75E-02"},{"id":"256751","name":"開田さんの怪談","type":1,"ratingTotal":11,"ratingScore":6.4,"tags":{},"RelationScore":"3.75E-02"},{"id":"217711","name":"芦屋さんの猫。","type":1,"ratingTotal":0,"ratingScore":0,"tags":{"一般向漫画":1,"日本漫画":1},"RelationScore":"3.75E-02"},{"id":"220580","name":"包丁さんのうわさ","type":1,"ratingTotal":2,"ratingScore":2.5,"tags":{},"RelationScore":"3.75E-02"},{"id":"20641","name":"姫宮さんの中の人","type":1,"ratingTotal":8,"ratingScore":6.9,"tags":{},"RelationScore":"3.75E-02"},{"id":"20636","name":"姫宮さんの中の人","type":1,"ratingTotal":5,"ratingScore":6.6,"tags":{},"RelationScore":"3.75E-02"},{"id":"311528","name":"村又さんの秘密","type":2,"ratingTotal":33,"ratingScore":5,"tags":{},"RelationScore":"3.75E-02"},{"id":"211331","name":"人外さんの嫁","type":1,"ratingTotal":5,"ratingScore":7,"tags":{},"RelationScore":"3.75E-02"},{"id":"91516","name":"ニシキくんのなすがまま","type":1,"ratingTotal":17,"ratingScore":5.8,"tags":{"少女マンガ":1,"乙女心":1,"漫画":1,"白石ユキ":1,"白石由希":1,"少女漫":1,"少女漫画":1,"少女":1},"RelationScore":"3.636363636363637E-02"}]