[{"id":"65447","name":"GOLDEN★AGE","type":1,"ratingTotal":0,"ratingScore":0,"tags":{},"RelationScore":"5E-02"},{"id":"57077","name":"CLEAVAGE","type":4,"ratingTotal":45,"ratingScore":5.8,"tags":{},"RelationScore":"5E-02"},{"id":"63037","name":"CLEAVAGE","type":2,"ratingTotal":141,"ratingScore":5.9,"tags":{},"RelationScore":"5E-02"},{"id":"39081","name":"D・N・ANGEL","type":1,"ratingTotal":32,"ratingScore":7,"tags":{},"RelationScore":"4.4444444444444446E-02"},{"id":"8202","name":"ALAN WAKE","type":4,"ratingTotal":193,"ratingScore":7.6,"tags":{},"RelationScore":"4.4444444444444446E-02"},{"id":"1651","name":"LIAR GAME","type":1,"ratingTotal":336,"ratingScore":8.1,"tags":{},"RelationScore":"4.4444444444444446E-02"},{"id":"1978","name":"D・N・ANGEL","type":2,"ratingTotal":848,"ratingScore":6.9,"tags":{},"RelationScore":"4.4444444444444446E-02"},{"id":"24374","name":"LIFE","type":3,"ratingTotal":52,"ratingScore":8.1,"tags":{},"RelationScore":"4.2857142857142864E-02"},{"id":"8904","name":"HIKARI","type":3,"ratingTotal":69,"ratingScore":7.7,"tags":{},"RelationScore":"4.2857142857142864E-02"},{"id":"47447","name":"KINGS","type":3,"ratingTotal":95,"ratingScore":7.2,"tags":{},"RelationScore":"4.2857142857142864E-02"}]