[{"id":"233946","name":"おいしいベランダ。","type":1,"ratingTotal":0,"ratingScore":0,"tags":{},"RelationScore":"4.5E-02"},{"id":"291666","name":"おいしいコーヒーのいれ方","type":1,"ratingTotal":3,"ratingScore":7.3,"tags":{"青沼裕貴":1,"JUMP+":1,"漫画":1},"RelationScore":"2.5E-02"},{"id":"149627","name":"真夜中のパン屋さん 午前0時のレシピ","type":1,"ratingTotal":0,"ratingScore":0,"tags":{},"RelationScore":"2.5E-02"},{"id":"217739","name":"まいごなぼくらの旅ごはん","type":1,"ratingTotal":1,"ratingScore":8,"tags":{},"RelationScore":"2.5E-02"},{"id":"211","name":"おいでよ どうぶつの森","type":4,"ratingTotal":170,"ratingScore":8,"tags":{},"RelationScore":"1.9999999999999997E-02"},{"id":"170868","name":"衛宮さんちの今日のごはん","type":1,"ratingTotal":30,"ratingScore":7.5,"tags":{},"RelationScore":"1.9999999999999997E-02"},{"id":"234349","name":"衛宮さんちの今日のごはん","type":2,"ratingTotal":2731,"ratingScore":7.6,"tags":{},"RelationScore":"1.9999999999999997E-02"},{"id":"22592","name":"やさしい竜の殺し方 (1)","type":1,"ratingTotal":2,"ratingScore":8,"tags":{},"RelationScore":"1.9999999999999997E-02"},{"id":"242123","name":"モンスター娘のお医者さん","type":1,"ratingTotal":5,"ratingScore":7.2,"tags":{"屎":1},"RelationScore":"1.9999999999999997E-02"},{"id":"84008","name":"おっぱいスライダー2","type":4,"ratingTotal":29,"ratingScore":6.3,"tags":{},"RelationScore":"1.9999999999999997E-02"}]