[{"id":"316168","name":"堂島くんは動じない","type":1,"ratingTotal":1,"ratingScore":6,"tags":{"漫画系列":1,"恋爱":1},"RelationScore":"4.166666666666666E-02"},{"id":"188518","name":"江口くんは見逃さない","type":1,"ratingTotal":21,"ratingScore":7,"tags":{},"RelationScore":"4.166666666666666E-02"},{"id":"299019","name":"山口くんはワルくない","type":1,"ratingTotal":0,"ratingScore":0,"tags":{},"RelationScore":"4.166666666666666E-02"},{"id":"226734","name":"多田くんは恋をしない","type":2,"ratingTotal":1340,"ratingScore":6.3,"tags":{},"RelationScore":"4.166666666666666E-02"},{"id":"213814","name":"漫画家ちゃんは眠れない","type":1,"ratingTotal":5,"ratingScore":7.6,"tags":{},"RelationScore":"4.166666666666666E-02"},{"id":"207883","name":"阿波連さんははかれない","type":1,"ratingTotal":110,"ratingScore":7.4,"tags":{},"RelationScore":"4.166666666666666E-02"},{"id":"103085","name":"小森さんは断れない！","type":1,"ratingTotal":19,"ratingScore":7.1,"tags":{},"RelationScore":"3.333333333333334E-02"},{"id":"240039","name":"ブギーポップは笑わない","type":2,"ratingTotal":2321,"ratingScore":7.3,"tags":{},"RelationScore":"3.333333333333334E-02"},{"id":"258205","name":"幽子さんは見られたい","type":1,"ratingTotal":5,"ratingScore":6.6,"tags":{},"RelationScore":"3.333333333333334E-02"},{"id":"14407","name":"ブギーポップは笑わない","type":1,"ratingTotal":33,"ratingScore":8.1,"tags":{},"RelationScore":"3.333333333333334E-02"}]