[{"id":"145908","name":"三者三葉","type":2,"ratingTotal":1012,"ratingScore":6.9,"tags":{},"RelationScore":"1E-01"},{"id":"79392","name":"三千世界","type":3,"ratingTotal":42,"ratingScore":6.8,"tags":{},"RelationScore":"2.5E-02"},{"id":"207343","name":"賢者の孫","type":1,"ratingTotal":11,"ratingScore":4.5,"tags":{},"RelationScore":"2.5E-02"},{"id":"23446","name":"Q版三国","type":2,"ratingTotal":319,"ratingScore":6.8,"tags":{},"RelationScore":"2.5E-02"},{"id":"68656","name":"言ノ葉","type":3,"ratingTotal":132,"ratingScore":7.8,"tags":{},"RelationScore":"2.5E-02"},{"id":"137576","name":"暗闇三太","type":2,"ratingTotal":30,"ratingScore":5.4,"tags":{},"RelationScore":"2.5E-02"},{"id":"108289","name":"聖者たち","type":3,"ratingTotal":72,"ratingScore":6.9,"tags":{},"RelationScore":"2.5E-02"},{"id":"1532","name":"三十路岬","type":3,"ratingTotal":131,"ratingScore":7.4,"tags":{},"RelationScore":"2.5E-02"},{"id":"288314","name":"愚者の星","type":1,"ratingTotal":2,"ratingScore":5.5,"tags":{},"RelationScore":"2.5E-02"},{"id":"49593","name":"恋染紅葉","type":1,"ratingTotal":94,"ratingScore":6.4,"tags":{},"RelationScore":"2.5E-02"}]