[{"id":"11736","name":"ファイナルファンタジーIX","type":4,"ratingTotal":174,"ratingScore":8.8,"tags":{},"RelationScore":"3.1578947368421054E-02"},{"id":"1259","name":"ファイナルファンタジーVII","type":4,"ratingTotal":409,"ratingScore":8.6,"tags":{},"RelationScore":"3.1578947368421054E-02"},{"id":"3692","name":"ファイナルファンタジーVIII","type":4,"ratingTotal":199,"ratingScore":8.3,"tags":{},"RelationScore":"3.1578947368421054E-02"},{"id":"2692","name":"ファイナルファンタジーXII","type":4,"ratingTotal":155,"ratingScore":8.3,"tags":{},"RelationScore":"3.1578947368421054E-02"},{"id":"163279","name":"ジョリーロジャー☆ファンタジー","type":1,"ratingTotal":0,"ratingScore":0,"tags":{},"RelationScore":"3.1578947368421054E-02"},{"id":"133969","name":"グランブルーファンタジー","type":1,"ratingTotal":0,"ratingScore":0,"tags":{},"RelationScore":"3.1578947368421054E-02"},{"id":"11734","name":"ファイナルファンタジーII","type":4,"ratingTotal":80,"ratingScore":7.3,"tags":{},"RelationScore":"3.1578947368421054E-02"},{"id":"13522","name":"ファイナルファンタジー","type":4,"ratingTotal":98,"ratingScore":7,"tags":{},"RelationScore":"3.1578947368421054E-02"},{"id":"79403","name":"巨乳ファンタジー","type":4,"ratingTotal":70,"ratingScore":7.3,"tags":{},"RelationScore":"3.1578947368421054E-02"},{"id":"127","name":"ファイナルファンタジーIV","type":4,"ratingTotal":170,"ratingScore":7.6,"tags":{},"RelationScore":"3.1578947368421054E-02"}]