[{"id":"46079","name":"今日のあすかショー","type":2,"ratingTotal":520,"ratingScore":7,"tags":{},"RelationScore":"2.5E-02"},{"id":"113121","name":"昨夜のカレー、明日のパン","type":6,"ratingTotal":54,"ratingScore":7.8,"tags":{},"RelationScore":"2.5E-02"},{"id":"9564","name":"明日のナージャ","type":2,"ratingTotal":174,"ratingScore":7.6,"tags":{},"RelationScore":"2.5E-02"},{"id":"214024","name":"今日、カレー!","type":1,"ratingTotal":8,"ratingScore":7,"tags":{},"RelationScore":"2.5E-02"},{"id":"322669","name":"今日のちょーか！","type":1,"ratingTotal":0,"ratingScore":0,"tags":{},"RelationScore":"2.5E-02"},{"id":"37843","name":"今日のあすかショー","type":1,"ratingTotal":59,"ratingScore":7.4,"tags":{},"RelationScore":"2.5E-02"},{"id":"50945","name":"今日のあすかショー OAD","type":2,"ratingTotal":159,"ratingScore":6.6,"tags":{},"RelationScore":"2.5E-02"},{"id":"78226","name":"えんどうくんの観察日記","type":1,"ratingTotal":32,"ratingScore":7.5,"tags":{},"RelationScore":"2.5E-02"},{"id":"23537","name":"ポヨポヨ観察日記","type":2,"ratingTotal":702,"ratingScore":7.5,"tags":{},"RelationScore":"2.5E-02"},{"id":"302851","name":"今日もカレーですか？","type":1,"ratingTotal":0,"ratingScore":0,"tags":{"漫画":1},"RelationScore":"2.5E-02"}]