[{"id":"4867","name":"僕は友達が少ない 2","type":1,"ratingTotal":128,"ratingScore":7.7,"tags":{},"RelationScore":"6.428571428571428E-02"},{"id":"18187","name":"僕は友達が少ない 6","type":1,"ratingTotal":90,"ratingScore":7.5,"tags":{},"RelationScore":"6.428571428571428E-02"},{"id":"22871","name":"僕は友達が少ない 7","type":1,"ratingTotal":67,"ratingScore":7.4,"tags":{},"RelationScore":"6.428571428571428E-02"},{"id":"11572","name":"僕は友達が少ない 5","type":1,"ratingTotal":105,"ratingScore":7.7,"tags":{},"RelationScore":"6.428571428571428E-02"},{"id":"8588","name":"僕は友達が少ない 4","type":1,"ratingTotal":115,"ratingScore":7.7,"tags":{},"RelationScore":"6.428571428571428E-02"},{"id":"49983","name":"僕は友達が少ない 第0話","type":2,"ratingTotal":823,"ratingScore":6.4,"tags":{},"RelationScore":"6.428571428571428E-02"},{"id":"41479","name":"僕は友達が少ない 8","type":1,"ratingTotal":35,"ratingScore":7.4,"tags":{},"RelationScore":"6.428571428571428E-02"},{"id":"4842","name":"僕は友達が少ない 3","type":1,"ratingTotal":120,"ratingScore":7.7,"tags":{},"RelationScore":"6.428571428571428E-02"},{"id":"149744","name":"僕は友達が少ない はがない日和","type":1,"ratingTotal":3,"ratingScore":3.3,"tags":{},"RelationScore":"6E-02"},{"id":"39699","name":"僕は友達が少ない あどおんでぃすく","type":2,"ratingTotal":984,"ratingScore":6.7,"tags":{},"RelationScore":"5.882352941176471E-02"}]