[{"id":"61509","name":"妖怪ウォッチ","type":4,"ratingTotal":22,"ratingScore":7.2,"tags":{},"RelationScore":"4.2857142857142864E-02"},{"id":"279472","name":"妖怪ウォッチ！","type":2,"ratingTotal":4,"ratingScore":6.3,"tags":{},"RelationScore":"4.2857142857142864E-02"},{"id":"83124","name":"妖怪ウォッチ","type":2,"ratingTotal":157,"ratingScore":7.3,"tags":{},"RelationScore":"4.2857142857142864E-02"},{"id":"2939","name":"ウィッチブレイド","type":2,"ratingTotal":204,"ratingScore":6.6,"tags":{},"RelationScore":"3.571428571428571E-02"},{"id":"292298","name":"シャドウバース","type":2,"ratingTotal":184,"ratingScore":3.7,"tags":{},"RelationScore":"2.8571428571428567E-02"},{"id":"111800","name":"ウィッチブレイド丈琉","type":1,"ratingTotal":2,"ratingScore":5,"tags":{},"RelationScore":"2.8571428571428567E-02"},{"id":"91848","name":"妹! アンドロイド","type":1,"ratingTotal":11,"ratingScore":5.9,"tags":{},"RelationScore":"2.8571428571428567E-02"},{"id":"185359","name":"シャドウバース","type":4,"ratingTotal":265,"ratingScore":6.8,"tags":{},"RelationScore":"2.8571428571428567E-02"},{"id":"27774","name":"鋼殻のレギオス シークレット・サイド","type":1,"ratingTotal":0,"ratingScore":0,"tags":{},"RelationScore":"2.7777777777777776E-02"},{"id":"139292","name":"サノバウィッチ オリジナル・サウンドトラック","type":3,"ratingTotal":34,"ratingScore":7.2,"tags":{},"RelationScore":"2.727272727272727E-02"}]