[{"id":"38067","name":"素晴らしき世界","type":3,"ratingTotal":41,"ratingScore":7.5,"tags":{},"RelationScore":"4.2857142857142864E-02"},{"id":"151450","name":"うるきゅー","type":1,"ratingTotal":0,"ratingScore":0,"tags":{},"RelationScore":"3.333333333333334E-02"},{"id":"321617","name":"新世界","type":2,"ratingTotal":2,"ratingScore":6,"tags":{"2020":1,"短片":1},"RelationScore":"3.333333333333334E-02"},{"id":"127607","name":"四次元世界","type":1,"ratingTotal":2,"ratingScore":8.5,"tags":{},"RelationScore":"3.333333333333334E-02"},{"id":"2450","name":"成恵の世界","type":2,"ratingTotal":108,"ratingScore":6.3,"tags":{},"RelationScore":"3.333333333333334E-02"},{"id":"48737","name":"夢見る世界","type":3,"ratingTotal":21,"ratingScore":7.2,"tags":{},"RelationScore":"3.333333333333334E-02"},{"id":"87884","name":"五龍世界","type":1,"ratingTotal":5,"ratingScore":6.6,"tags":{"轻小说":1,"壁井":1,"壁井ユカコ":1,"好而冷":1},"RelationScore":"3.333333333333334E-02"},{"id":"316517","name":"新世界","type":3,"ratingTotal":0,"ratingScore":0,"tags":{},"RelationScore":"3.333333333333334E-02"},{"id":"79392","name":"三千世界","type":3,"ratingTotal":42,"ratingScore":6.8,"tags":{},"RelationScore":"3.333333333333334E-02"},{"id":"80913","name":"凹凸世界","type":2,"ratingTotal":188,"ratingScore":6.7,"tags":{},"RelationScore":"3.333333333333334E-02"}]