[{"id":"207485","name":"毒贄のサクリ","type":1,"ratingTotal":2,"ratingScore":3,"tags":{"漫画":1},"RelationScore":"8.25E-01"},{"id":"281158","name":"ナゲキの幽便屋","type":1,"ratingTotal":0,"ratingScore":0,"tags":{"漫画":1},"RelationScore":"8.25E-01"},{"id":"101544","name":"らのべのへん！","type":1,"ratingTotal":2,"ratingScore":4.5,"tags":{"漫画":1},"RelationScore":"8.25E-01"},{"id":"178259","name":"ブリキの缶づめ","type":1,"ratingTotal":0,"ratingScore":0,"tags":{"漫画":1},"RelationScore":"8.25E-01"},{"id":"98567","name":"テイルズ オブ ヴェスペリア","type":1,"ratingTotal":1,"ratingScore":7,"tags":{"漫画":1},"RelationScore":"8.214285714285714E-01"},{"id":"290396","name":"トリニティセブン アナスタシア聖伝","type":1,"ratingTotal":0,"ratingScore":0,"tags":{"漫画":1},"RelationScore":"8.176470588235294E-01"},{"id":"182037","name":"ないしょの乙女リボルバー","type":1,"ratingTotal":1,"ratingScore":5,"tags":{"漫画":1},"RelationScore":"8.166666666666668E-01"},{"id":"245140","name":"黒のカミサマと白のアデプト","type":1,"ratingTotal":0,"ratingScore":0,"tags":{"漫画":1},"RelationScore":"8.153846153846154E-01"},{"id":"18336","name":"殻都市の夢","type":1,"ratingTotal":20,"ratingScore":7.5,"tags":{"漫画":1},"RelationScore":"8.125E-01"},{"id":"179297","name":"オトナの証明","type":1,"ratingTotal":0,"ratingScore":0,"tags":{"漫画":1},"RelationScore":"8.125E-01"}]