[{"id":"121635","name":"瞳で私をつかまえて","type":1,"ratingTotal":1,"ratingScore":6,"tags":{"少女漫画":1},"RelationScore":"5.555555555555555E-02"},{"id":"21014","name":"カエル畑DEつかまえて☆彡","type":4,"ratingTotal":22,"ratingScore":7.1,"tags":{},"RelationScore":"3.846153846153846E-02"},{"id":"295962","name":"キミの忘れかたを教えて","type":1,"ratingTotal":0,"ratingScore":0,"tags":{},"RelationScore":"2.727272727272727E-02"},{"id":"38647","name":"ツレがうつになりまして。","type":6,"ratingTotal":80,"ratingScore":7.4,"tags":{},"RelationScore":"2.5E-02"},{"id":"209647","name":"ドラゴン嫁はかまってほしい","type":1,"ratingTotal":3,"ratingScore":4.3,"tags":{},"RelationScore":"2.3076923076923075E-02"},{"id":"210317","name":"陽下3姉妹はかまってほしい","type":1,"ratingTotal":21,"ratingScore":6.4,"tags":{},"RelationScore":"2.3076923076923075E-02"},{"id":"1856","name":"十二国記","type":2,"ratingTotal":2316,"ratingScore":8.3,"tags":{},"RelationScore":"2.2222222222222223E-02"},{"id":"107928","name":"ぐでたま","type":2,"ratingTotal":35,"ratingScore":7.3,"tags":{},"RelationScore":"2.2222222222222223E-02"},{"id":"230968","name":"旅かえる","type":4,"ratingTotal":136,"ratingScore":6.2,"tags":{},"RelationScore":"2.2222222222222223E-02"},{"id":"12521","name":"十二幻夢絵巻","type":3,"ratingTotal":46,"ratingScore":8.3,"tags":{},"RelationScore":"2.2222222222222223E-02"}]