[{"id":"43317","name":"轩辕剑之天之痕","type":6,"ratingTotal":27,"ratingScore":2.5,"tags":{},"RelationScore":"2.5E-02"},{"id":"277163","name":"妖神记之黑狱篇","type":2,"ratingTotal":5,"ratingScore":6.4,"tags":{},"RelationScore":"2.5E-02"},{"id":"262125","name":"妖神记之影妖篇","type":2,"ratingTotal":15,"ratingScore":6,"tags":{},"RelationScore":"2.5E-02"},{"id":"75618","name":"剣神の継承者","type":1,"ratingTotal":4,"ratingScore":5.5,"tags":{},"RelationScore":"2.5E-02"},{"id":"304668","name":"大话之少年游","type":2,"ratingTotal":2,"ratingScore":6,"tags":{},"RelationScore":"2.5E-02"},{"id":"46173","name":"剣神の継承者","type":1,"ratingTotal":21,"ratingScore":6.4,"tags":{},"RelationScore":"2.5E-02"},{"id":"231163","name":"望まぬ不死の冒険者","type":1,"ratingTotal":17,"ratingScore":6.6,"tags":{},"RelationScore":"2.2222222222222223E-02"},{"id":"231165","name":"望まぬ不死の冒険者","type":1,"ratingTotal":3,"ratingScore":5.7,"tags":{},"RelationScore":"2.2222222222222223E-02"},{"id":"320235","name":"长安十二时辰之白夜行者","type":2,"ratingTotal":0,"ratingScore":0,"tags":{"中国":1,"国产":1},"RelationScore":"1.8181818181818177E-02"},{"id":"231166","name":"望まぬ不死の冒険者 (1)","type":1,"ratingTotal":0,"ratingScore":0,"tags":{},"RelationScore":"1.5384615384615385E-02"}]