[{"id":"81709","name":"まほろまてぃっく","type":1,"ratingTotal":17,"ratingScore":6.8,"tags":{"漫画":1,"中山文十郎":1,"ぢたま某":1,"搜索用":1},"RelationScore":"4.2105263157894736E-02"},{"id":"2141","name":"まほろまてぃっく","type":2,"ratingTotal":745,"ratingScore":7.4,"tags":{},"RelationScore":"4.2105263157894736E-02"},{"id":"2729","name":"まほろまてぃっく特別編 ただいま◆おかえり","type":2,"ratingTotal":347,"ratingScore":7.2,"tags":{},"RelationScore":"3.809523809523809E-02"},{"id":"54727","name":"まほろまてぃっく夏のTVスペシャル 「えっちなのはいけないと思います!」","type":2,"ratingTotal":131,"ratingScore":6.9,"tags":{},"RelationScore":"3.0555555555555558E-02"},{"id":"9726","name":"まりあ†ほりっく あらいぶ","type":2,"ratingTotal":1656,"ratingScore":7.2,"tags":{},"RelationScore":"2.6315789473684213E-02"},{"id":"2167","name":"この醜くも美しい世界","type":2,"ratingTotal":483,"ratingScore":6.2,"tags":{},"RelationScore":"2.6315789473684213E-02"},{"id":"122654","name":"まほろばきっさ (1)","type":1,"ratingTotal":1,"ratingScore":7,"tags":{},"RelationScore":"2.6315789473684213E-02"},{"id":"111732","name":"まつろはぬもの 〜鬼の渡る古道〜","type":1,"ratingTotal":5,"ratingScore":6.2,"tags":{},"RelationScore":"2.6315789473684213E-02"},{"id":"99809","name":"召しませロードス島戦記 それっておいしいの？","type":2,"ratingTotal":46,"ratingScore":5.5,"tags":{},"RelationScore":"2.2727272727272728E-02"},{"id":"2617","name":"そらのおとしもの","type":2,"ratingTotal":3844,"ratingScore":7.1,"tags":{},"RelationScore":"2.1052631578947368E-02"}]