[{"id":"132017","name":"姑獲鳥の夏","type":1,"ratingTotal":26,"ratingScore":7.3,"tags":{},"RelationScore":"1E-01"},{"id":"132487","name":"菊次郎の夏","type":6,"ratingTotal":68,"ratingScore":7.6,"tags":{},"RelationScore":"4E-02"},{"id":"259191","name":"中3の夏","type":1,"ratingTotal":0,"ratingScore":0,"tags":{},"RelationScore":"4E-02"},{"id":"56665","name":"鳥の歌","type":2,"ratingTotal":70,"ratingScore":6.5,"tags":{},"RelationScore":"4E-02"},{"id":"194222","name":"はじまりの夏","type":1,"ratingTotal":3,"ratingScore":6.3,"tags":{},"RelationScore":"3.333333333333334E-02"},{"id":"2133","name":"官僚たちの夏","type":6,"ratingTotal":22,"ratingScore":7.5,"tags":{},"RelationScore":"3.333333333333334E-02"},{"id":"2312","name":"120円の夏","type":4,"ratingTotal":527,"ratingScore":7,"tags":{},"RelationScore":"3.333333333333334E-02"},{"id":"171116","name":"ぼくと未来屋の夏","type":1,"ratingTotal":1,"ratingScore":7,"tags":{},"RelationScore":"2.5E-02"},{"id":"241030","name":"君はまだ鳥籠の中","type":1,"ratingTotal":7,"ratingScore":6.3,"tags":{},"RelationScore":"2.5E-02"},{"id":"63386","name":"向日葵の咲かない夏","type":1,"ratingTotal":46,"ratingScore":7.1,"tags":{},"RelationScore":"2.2222222222222223E-02"}]