[{"id":"15921","name":"Morning Arch","type":3,"ratingTotal":36,"ratingScore":7.4,"tags":{},"RelationScore":"3.846153846153846E-02"},{"id":"215265","name":"Mourning Bride","type":1,"ratingTotal":7,"ratingScore":5.7,"tags":{},"RelationScore":"3.461538461538462E-02"},{"id":"211389","name":"Morning Glory","type":3,"ratingTotal":36,"ratingScore":7,"tags":{"樱花任务":1,"2017年":1,"OP":1,"(K)NoW_NAME":1,"2017":1,"NIKIIE":1},"RelationScore":"3.461538461538462E-02"},{"id":"321807","name":"Longing for! / まひるいろシエスタ","type":3,"ratingTotal":0,"ratingScore":0,"tags":{},"RelationScore":"3.076923076923077E-02"},{"id":"210879","name":"Mount \u0026 Blade II: Bannerlord","type":4,"ratingTotal":34,"ratingScore":7.7,"tags":{},"RelationScore":"2.8571428571428567E-02"},{"id":"94755","name":"Moving go on","type":3,"ratingTotal":22,"ratingScore":8.2,"tags":{"川村ゆみ":1,"galgame":1,"OP":1,"3days":1,"神曲":1,"Lass":1},"RelationScore":"2.6923076923076925E-02"},{"id":"317876","name":"Mondo Trasho 3042","type":2,"ratingTotal":0,"ratingScore":0,"tags":{"WEB":1},"RelationScore":"2.6923076923076925E-02"},{"id":"19873","name":"Mount \u0026 Blade: Warband","type":4,"ratingTotal":327,"ratingScore":8.3,"tags":{},"RelationScore":"2.6923076923076925E-02"},{"id":"216435","name":"Loving Vincent","type":2,"ratingTotal":212,"ratingScore":7.2,"tags":{},"RelationScore":"2.6923076923076925E-02"},{"id":"4147","name":"sprinter / ARIA","type":3,"ratingTotal":222,"ratingScore":8.2,"tags":{},"RelationScore":"2.6923076923076925E-02"}]