[{"id":"222945","name":"SANITY:ZERO","type":1,"ratingTotal":4,"ratingScore":5,"tags":{},"RelationScore":"4.2105263157894736E-02"},{"id":"53413","name":"INNOCENCE O.S.T.","type":3,"ratingTotal":95,"ratingScore":8.8,"tags":{},"RelationScore":"3.1578947368421054E-02"},{"id":"313828","name":"色欲INFINITE","type":2,"ratingTotal":53,"ratingScore":5.5,"tags":{},"RelationScore":"3.1578947368421054E-02"},{"id":"291345","name":"色欲INFINITE","type":1,"ratingTotal":22,"ratingScore":6.8,"tags":{},"RelationScore":"3.1578947368421054E-02"},{"id":"10518","name":"OFFICIAL ORANGE","type":3,"ratingTotal":39,"ratingScore":7.9,"tags":{},"RelationScore":"3.1578947368421054E-02"},{"id":"1057","name":"Ys II ETERNAL","type":4,"ratingTotal":240,"ratingScore":8.1,"tags":{},"RelationScore":"3.1578947368421054E-02"},{"id":"221040","name":"FINAL FANTASY LOST STRANGER","type":1,"ratingTotal":0,"ratingScore":0,"tags":{},"RelationScore":"2.9629629629629627E-02"},{"id":"723","name":"FINAL FANTASY TACTICS ADVANCE","type":4,"ratingTotal":215,"ratingScore":8.3,"tags":{},"RelationScore":"2.7586206896551727E-02"},{"id":"19518","name":"MIKUNOPOLIS in LOS ANGELES","type":3,"ratingTotal":21,"ratingScore":8.7,"tags":{},"RelationScore":"2.6923076923076925E-02"},{"id":"710","name":"FINAL FANTASY I・II ADVANCE","type":4,"ratingTotal":33,"ratingScore":7,"tags":{"ff":1,"汉化":1,"RPG":1,"GBA":1},"RelationScore":"2.6923076923076925E-02"}]