[{"id":"66526","name":"聲の形","type":1,"ratingTotal":225,"ratingScore":7.5,"tags":{},"RelationScore":"5E-02"},{"id":"80979","name":"聲の形","type":1,"ratingTotal":524,"ratingScore":7.6,"tags":{},"RelationScore":"5E-02"},{"id":"290993","name":"映画 ギヴン","type":2,"ratingTotal":2,"ratingScore":7,"tags":{},"RelationScore":"5E-02"},{"id":"120376","name":"映画 HERO","type":6,"ratingTotal":24,"ratingScore":6.7,"tags":{},"RelationScore":"4.2857142857142864E-02"},{"id":"256681","name":"映画 賭ケグルイ","type":6,"ratingTotal":21,"ratingScore":6.4,"tags":{},"RelationScore":"3.75E-02"},{"id":"120700","name":"蟲師 鈴の雫","type":2,"ratingTotal":1110,"ratingScore":8.3,"tags":{},"RelationScore":"3.333333333333334E-02"},{"id":"102123","name":"竜の涙 聲の羅針盤","type":3,"ratingTotal":23,"ratingScore":6.6,"tags":{},"RelationScore":"3.333333333333334E-02"},{"id":"191662","name":"映画 咲-Saki-","type":6,"ratingTotal":32,"ratingScore":6.8,"tags":{},"RelationScore":"3.0000000000000006E-02"},{"id":"92418","name":"家族計画 ～絆の響～","type":3,"ratingTotal":59,"ratingScore":8.4,"tags":{},"RelationScore":"3.0000000000000006E-02"},{"id":"241527","name":"青の花 器の森","type":1,"ratingTotal":0,"ratingScore":0,"tags":{"恋爱":1,"心像汉化组":1,"小玉ユキ":1},"RelationScore":"2.8571428571428567E-02"}]