[{"id":"135271","name":"恋文日和","type":1,"ratingTotal":0,"ratingScore":0,"tags":{"已完结":1,"漫画系列":1},"RelationScore":"5E-02"},{"id":"223850","name":"小春日和","type":1,"ratingTotal":0,"ratingScore":0,"tags":{"漫画系列":1},"RelationScore":"5E-02"},{"id":"46211","name":"咲日和","type":1,"ratingTotal":23,"ratingScore":7.3,"tags":{},"RelationScore":"5E-02"},{"id":"8937","name":"桜日和","type":3,"ratingTotal":33,"ratingScore":8,"tags":{},"RelationScore":"5E-02"},{"id":"3215","name":"リンゴ日和","type":3,"ratingTotal":131,"ratingScore":7.5,"tags":{},"RelationScore":"4E-02"},{"id":"75162","name":"秋色妄想日和","type":1,"ratingTotal":11,"ratingScore":5.6,"tags":{"河下水希":1,"短篇":1,"漫画":1,"短篇漫画":1,"集英社":1},"RelationScore":"3.333333333333334E-02"},{"id":"91866","name":"おきつね日和","type":1,"ratingTotal":5,"ratingScore":5.6,"tags":{},"RelationScore":"3.333333333333334E-02"},{"id":"83726","name":"のんのん日和","type":3,"ratingTotal":71,"ratingScore":7.4,"tags":{},"RelationScore":"3.333333333333334E-02"},{"id":"110884","name":"徒然チルドレン","type":1,"ratingTotal":117,"ratingScore":7.4,"tags":{},"RelationScore":"2.8571428571428567E-02"},{"id":"208754","name":"徒然チルドレン","type":2,"ratingTotal":2696,"ratingScore":7.2,"tags":{},"RelationScore":"2.8571428571428567E-02"}]