[{"id":"6494","name":"the monochrome disc","type":3,"ratingTotal":32,"ratingScore":8.3,"tags":{"入手":1,"中毒":1,"2009":1,"Vocaloid":1,"wowaka":1,"現実逃避P":1,"初音ミク":1,"wowaka／現実逃避P":1,"VM10":1,"音乐专辑":1,"album":1},"RelationScore":"3.4112114616897665E-01"},{"id":"149631","name":"ゲート―自衛隊 彼の地にて、斯く戦えり〈1〉接触編","type":1,"ratingTotal":1,"ratingScore":7,"tags":{"2010":1},"RelationScore":"2.86842712474619E-01"},{"id":"10535","name":"EXIT TUNES PRESENTS Supernova4","type":3,"ratingTotal":21,"ratingScore":7.4,"tags":{"Vocaloid":1,"supernova":1,"★Vocaloid":1,"V.A.":1,"2010":1},"RelationScore":"2.563155461468037E-01"},{"id":"10736","name":"supercell tribute～Stowaways～/ supercell feat.初音ミク","type":3,"ratingTotal":44,"ratingScore":7.2,"tags":{"miku":1,"minato(流星P)":1,"Remix":1,"2010":1,"Vocaloid":1,"初音ミク":1,"doriko":1,"album":1,"小林オニキス":1,"v家":1,"ryo":1,"supercell":1},"RelationScore":"2.5107142325790965E-01"},{"id":"133705","name":"花と水飴、最終電車","type":3,"ratingTotal":36,"ratingScore":8.4,"tags":{"Vocaloid":1,"n-buna":1,"夏":1,"ナブナ":1,"album":1,"邦摇":1},"RelationScore":"2.3094010767585033E-01"},{"id":"190709","name":"月を歩いている","type":3,"ratingTotal":25,"ratingScore":8,"tags":{"2016":1,"Vocaloid":1,"ナブナ":1,"n-buna":1,"邦摇":1,"album":1},"RelationScore":"2.3094010767585033E-01"},{"id":"53243","name":"Go for it!!","type":1,"ratingTotal":0,"ratingScore":0,"tags":{"2010":1,"BL漫画":1},"RelationScore":"2.125E-01"},{"id":"196605","name":"リンちゃんなう ver.0","type":1,"ratingTotal":0,"ratingScore":0,"tags":{"已完结":1,"Vocaloid":1},"RelationScore":"2E-01"},{"id":"36977","name":"幻実アイソーポス(初回生産限定盤)(DVD付)","type":3,"ratingTotal":28,"ratingScore":8.1,"tags":{"sasakure.UK":1,"Vocaloid":1},"RelationScore":"2E-01"},{"id":"195159","name":"竹取オーバーナイトセンセーション","type":1,"ratingTotal":0,"ratingScore":0,"tags":{"音乐改":1,"Vocaloid":1},"RelationScore":"2E-01"}]