[{"id":"25502","name":"哀しみキメラ","type":1,"ratingTotal":9,"ratingScore":7.2,"tags":{"系列":1,"来楽零":1,"轻小说":1,"未読":1,"小説":1,"幻想":1},"RelationScore":"4.4444444444444446E-02"},{"id":"10442","name":"哀しみキメラ〈1〉","type":1,"ratingTotal":7,"ratingScore":7.6,"tags":{},"RelationScore":"4.4444444444444446E-02"},{"id":"45499","name":"花冠のマドンナ","type":1,"ratingTotal":4,"ratingScore":6,"tags":{},"RelationScore":"4.4444444444444446E-02"},{"id":"23884","name":"しにがみのバラッド。01","type":1,"ratingTotal":8,"ratingScore":7.5,"tags":{},"RelationScore":"3.333333333333334E-02"},{"id":"58677","name":"双子座のパラドクス","type":4,"ratingTotal":22,"ratingScore":6.9,"tags":{},"RelationScore":"3.333333333333334E-02"},{"id":"217837","name":"台所のドラゴン","type":1,"ratingTotal":1,"ratingScore":7,"tags":{},"RelationScore":"3.333333333333334E-02"},{"id":"77471","name":"ガリレイドンナ","type":2,"ratingTotal":1190,"ratingScore":5.8,"tags":{},"RelationScore":"3.333333333333334E-02"},{"id":"275461","name":"死神のラメント","type":1,"ratingTotal":0,"ratingScore":0,"tags":{},"RelationScore":"3.333333333333334E-02"},{"id":"23896","name":"しにがみのバラッド。","type":1,"ratingTotal":34,"ratingScore":7.3,"tags":{},"RelationScore":"3.0000000000000006E-02"},{"id":"161959","name":"哀しみが時代を駆ける","type":3,"ratingTotal":23,"ratingScore":7.9,"tags":{},"RelationScore":"3.0000000000000006E-02"}]