[{"id":"139408","name":"おそ松さん","type":2,"ratingTotal":1865,"ratingScore":7.5,"tags":{},"RelationScore":"5.555555555555555E-02"},{"id":"2639","name":"歌のおにいさん","type":6,"ratingTotal":37,"ratingScore":7,"tags":{},"RelationScore":"4.4444444444444446E-02"},{"id":"304468","name":"国宝のお医者さん","type":1,"ratingTotal":0,"ratingScore":0,"tags":{"漫画":1,"漫画系列":1},"RelationScore":"4.4444444444444446E-02"},{"id":"211916","name":"三匹のおっさん","type":1,"ratingTotal":1,"ratingScore":8,"tags":{},"RelationScore":"4.4444444444444446E-02"},{"id":"211915","name":"三匹のおっさん","type":1,"ratingTotal":1,"ratingScore":8,"tags":{},"RelationScore":"4.4444444444444446E-02"},{"id":"23107","name":"妖怪のお医者さん","type":1,"ratingTotal":4,"ratingScore":6,"tags":{},"RelationScore":"4.4444444444444446E-02"},{"id":"48882","name":"ちいさなおじさん","type":2,"ratingTotal":200,"ratingScore":6.1,"tags":{},"RelationScore":"4.4444444444444446E-02"},{"id":"172317","name":"キックのお姉さん","type":1,"ratingTotal":4,"ratingScore":5.8,"tags":{},"RelationScore":"4.4444444444444446E-02"},{"id":"148900","name":"おそ松くん","type":1,"ratingTotal":1,"ratingScore":9,"tags":{},"RelationScore":"4.4444444444444446E-02"},{"id":"258397","name":"おもいがおもいおもいさん","type":1,"ratingTotal":7,"ratingScore":6.6,"tags":{},"RelationScore":"4.166666666666666E-02"}]