[{"id":"42297","name":"BRAVE BLADE!","type":3,"ratingTotal":22,"ratingScore":6.3,"tags":{},"RelationScore":"5E-02"},{"id":"8562","name":"BAMBOO BLADE","type":1,"ratingTotal":48,"ratingScore":7.5,"tags":{},"RelationScore":"5E-02"},{"id":"4338","name":"ETERNAL BLAZE","type":3,"ratingTotal":113,"ratingScore":8.1,"tags":{},"RelationScore":"4.6153846153846156E-02"},{"id":"48392","name":"NANA BEST","type":3,"ratingTotal":34,"ratingScore":8.4,"tags":{},"RelationScore":"4.5454545454545456E-02"},{"id":"10601","name":"BLADE","type":2,"ratingTotal":137,"ratingScore":5.6,"tags":{},"RelationScore":"4.5454545454545456E-02"},{"id":"40110","name":"XBLADE","type":1,"ratingTotal":5,"ratingScore":5.4,"tags":{},"RelationScore":"4.5454545454545456E-02"},{"id":"41077","name":"NINJA GAIDEN Black","type":4,"ratingTotal":23,"ratingScore":8.9,"tags":{},"RelationScore":"4.4444444444444446E-02"},{"id":"135999","name":"NiTRO+ BLASTERZ","type":4,"ratingTotal":28,"ratingScore":6.3,"tags":{},"RelationScore":"4E-02"},{"id":"28756","name":"AMNESIA LATER","type":4,"ratingTotal":165,"ratingScore":7.2,"tags":{},"RelationScore":"3.846153846153846E-02"},{"id":"60913","name":"NINJA GAIDEN 2 Σ Plus","type":4,"ratingTotal":62,"ratingScore":6.5,"tags":{},"RelationScore":"3.809523809523809E-02"}]