[{"id":"3128","name":"デジモンアドベンチャー","type":2,"ratingTotal":4533,"ratingScore":8.3,"tags":{},"RelationScore":"3.181818181818183E-02"},{"id":"106291","name":"RGBアドベンチャー","type":2,"ratingTotal":0,"ratingScore":0,"tags":{},"RelationScore":"3.181818181818183E-02"},{"id":"3133","name":"デジモンアドベンチャー","type":2,"ratingTotal":769,"ratingScore":7.7,"tags":{},"RelationScore":"3.181818181818183E-02"},{"id":"298451","name":"デジモンアドベンチャー：","type":2,"ratingTotal":152,"ratingScore":6.6,"tags":{},"RelationScore":"3.181818181818183E-02"},{"id":"3129","name":"デジモンアドベンチャー02","type":2,"ratingTotal":1305,"ratingScore":6.9,"tags":{},"RelationScore":"3.181818181818183E-02"},{"id":"60380","name":"デジモン アドベンチャー","type":4,"ratingTotal":73,"ratingScore":7.2,"tags":{},"RelationScore":"3.181818181818183E-02"},{"id":"154112","name":"ONE PIECE 〜アドベンチャー オブ ネブランディア〜","type":2,"ratingTotal":62,"ratingScore":6.1,"tags":{},"RelationScore":"2.666666666666667E-02"},{"id":"104354","name":"おしゃぶりアナウンサー","type":2,"ratingTotal":96,"ratingScore":5.7,"tags":{},"RelationScore":"2.2727272727272728E-02"},{"id":"146186","name":"アルティメット・アンチヒーロー","type":1,"ratingTotal":3,"ratingScore":5.7,"tags":{},"RelationScore":"2.2727272727272728E-02"},{"id":"139130","name":"アルティメット・アンチヒーロー","type":1,"ratingTotal":0,"ratingScore":0,"tags":{},"RelationScore":"2.2727272727272728E-02"}]