[{"id":"105852","name":"腐女子彼女。","type":1,"ratingTotal":1,"ratingScore":7,"tags":{"小说":1},"RelationScore":"3.333333333333334E-02"},{"id":"140540","name":"少女交響曲","type":3,"ratingTotal":26,"ratingScore":7.2,"tags":{},"RelationScore":"3.333333333333334E-02"},{"id":"73644","name":"少女恋愛変異","type":1,"ratingTotal":13,"ratingScore":5.1,"tags":{"性转":1,"屎":1,"BG":1},"RelationScore":"3.333333333333334E-02"},{"id":"227245","name":"少女週末授業","type":2,"ratingTotal":324,"ratingScore":6.5,"tags":{},"RelationScore":"3.333333333333334E-02"},{"id":"53875","name":"腐女子彼女。","type":1,"ratingTotal":7,"ratingScore":7.6,"tags":{},"RelationScore":"3.333333333333334E-02"},{"id":"187498","name":"少女ペット","type":1,"ratingTotal":8,"ratingScore":3.8,"tags":{},"RelationScore":"3.333333333333334E-02"},{"id":"288194","name":"妄想破绽","type":4,"ratingTotal":34,"ratingScore":4.4,"tags":{},"RelationScore":"3.333333333333334E-02"},{"id":"282910","name":"乙女どもよ。","type":3,"ratingTotal":98,"ratingScore":8.1,"tags":{},"RelationScore":"3.333333333333334E-02"},{"id":"75162","name":"秋色妄想日和","type":1,"ratingTotal":11,"ratingScore":5.6,"tags":{"漫画":1,"短篇漫画":1,"集英社":1,"河下水希":1,"短篇":1},"RelationScore":"3.333333333333334E-02"},{"id":"5968","name":"少女セクト","type":1,"ratingTotal":78,"ratingScore":7.2,"tags":{},"RelationScore":"3.333333333333334E-02"}]