[{"id":"41469","name":"俺が彼女に迫られて、妹が怒ってる?1","type":1,"ratingTotal":6,"ratingScore":6,"tags":{},"RelationScore":"9.444444444444444E-02"},{"id":"19438","name":"この中に1人、妹がいる！","type":1,"ratingTotal":63,"ratingScore":5.7,"tags":{},"RelationScore":"2.9411764705882346E-02"},{"id":"138986","name":"この中に1人、妹がいる!","type":1,"ratingTotal":3,"ratingScore":6.7,"tags":{},"RelationScore":"2.9411764705882346E-02"},{"id":"41028","name":"この中に1人、妹がいる!","type":2,"ratingTotal":1660,"ratingScore":5.6,"tags":{},"RelationScore":"2.9411764705882346E-02"},{"id":"36231","name":"俺は彼女を信じてる!","type":2,"ratingTotal":238,"ratingScore":6.2,"tags":{},"RelationScore":"2.9411764705882346E-02"},{"id":"313210","name":"親友の娘に迫られ困っています","type":1,"ratingTotal":1,"ratingScore":6,"tags":{},"RelationScore":"2.9411764705882346E-02"},{"id":"279871","name":"魔法少女にあこがれて","type":1,"ratingTotal":22,"ratingScore":7.7,"tags":{},"RelationScore":"2.352941176470589E-02"},{"id":"216481","name":"君に愛されて痛かった","type":1,"ratingTotal":13,"ratingScore":6.8,"tags":{},"RelationScore":"2.352941176470589E-02"},{"id":"144446","name":"兄に愛されすぎて困ってます","type":1,"ratingTotal":9,"ratingScore":6.3,"tags":{},"RelationScore":"2.352941176470589E-02"},{"id":"301498","name":"君が肉になっても","type":1,"ratingTotal":21,"ratingScore":5.4,"tags":{},"RelationScore":"2.352941176470589E-02"}]