[{"id":"8203","name":"of memories","type":3,"ratingTotal":33,"ratingScore":7.4,"tags":{},"RelationScore":"3.636363636363637E-02"},{"id":"133071","name":"The Terminator","type":6,"ratingTotal":55,"ratingScore":7.5,"tags":{},"RelationScore":"3.571428571428571E-02"},{"id":"141547","name":"Lifeline","type":4,"ratingTotal":140,"ratingScore":6.5,"tags":{},"RelationScore":"3.333333333333334E-02"},{"id":"143864","name":"Blue Destiny","type":3,"ratingTotal":27,"ratingScore":7.3,"tags":{},"RelationScore":"3.333333333333334E-02"},{"id":"127500","name":"Nein","type":3,"ratingTotal":47,"ratingScore":7.4,"tags":{},"RelationScore":"3.333333333333334E-02"},{"id":"232108","name":"Death Coming","type":4,"ratingTotal":27,"ratingScore":6.4,"tags":{},"RelationScore":"3.333333333333334E-02"},{"id":"173483","name":"Fluteman","type":1,"ratingTotal":1,"ratingScore":5,"tags":{},"RelationScore":"3.333333333333334E-02"},{"id":"216660","name":"For The King","type":4,"ratingTotal":33,"ratingScore":6.7,"tags":{},"RelationScore":"3.333333333333334E-02"},{"id":"228793","name":"behind","type":3,"ratingTotal":80,"ratingScore":7.9,"tags":{},"RelationScore":"3.333333333333334E-02"},{"id":"13008","name":"Megamind","type":2,"ratingTotal":262,"ratingScore":7,"tags":{},"RelationScore":"3.333333333333334E-02"}]