[{"id":"30991","name":"もうひとつの神話","type":1,"ratingTotal":7,"ratingScore":6.4,"tags":{},"RelationScore":"7.5E-02"},{"id":"91341","name":"もうひとつの未来を。","type":2,"ratingTotal":70,"ratingScore":5.6,"tags":{},"RelationScore":"6E-02"},{"id":"2161","name":"たったひとつの恋","type":6,"ratingTotal":112,"ratingScore":6.7,"tags":{},"RelationScore":"5E-02"},{"id":"208432","name":"ひとつばな","type":1,"ratingTotal":18,"ratingScore":5.7,"tags":{},"RelationScore":"4.2857142857142864E-02"},{"id":"78396","name":"どうぶつの国","type":1,"ratingTotal":11,"ratingScore":7.2,"tags":{},"RelationScore":"4.2857142857142864E-02"},{"id":"159821","name":"だがしかし もうひとつの夏休み","type":1,"ratingTotal":2,"ratingScore":6.5,"tags":{},"RelationScore":"4E-02"},{"id":"2314","name":"ノエイン もうひとりの君へ","type":2,"ratingTotal":316,"ratingScore":7.2,"tags":{},"RelationScore":"3.846153846153846E-02"},{"id":"21159","name":"願い事ひとつだけ","type":3,"ratingTotal":21,"ratingScore":8.5,"tags":{},"RelationScore":"3.75E-02"},{"id":"73835","name":"君とひみつの花園","type":1,"ratingTotal":3,"ratingScore":7.3,"tags":{},"RelationScore":"3.75E-02"},{"id":"270081","name":"天体のメソッド もうひとつの願い","type":2,"ratingTotal":255,"ratingScore":7.1,"tags":{},"RelationScore":"3.75E-02"}]