[{"id":"154986","name":"ダークロード  漆黒の断罪者","type":1,"ratingTotal":2,"ratingScore":7,"tags":{"轻小说":1,"小说":1},"RelationScore":"2.8571428571428567E-02"},{"id":"2605","name":"クイーンズブレイド 玉座を継ぐ者","type":2,"ratingTotal":511,"ratingScore":6.6,"tags":{},"RelationScore":"2.5E-02"},{"id":"53412","name":"ウォーレスの人魚","type":1,"ratingTotal":7,"ratingScore":7.6,"tags":{},"RelationScore":"2.5E-02"},{"id":"136516","name":"オーバーロード (9) 破軍の魔法詠唱者","type":1,"ratingTotal":21,"ratingScore":7.3,"tags":{"轻小说":1,"丸山くがね":1,"OVERLORD":1},"RelationScore":"2.5E-02"},{"id":"262889","name":"アーサー 復活の騎士王","type":2,"ratingTotal":19,"ratingScore":5.9,"tags":{},"RelationScore":"2.5E-02"},{"id":"2783","name":"名探偵コナン 漆黒の追跡者","type":2,"ratingTotal":1889,"ratingScore":6.7,"tags":{},"RelationScore":"2.3076923076923075E-02"},{"id":"290134","name":"幸色のワンルーム 外伝 正壊の名探偵","type":1,"ratingTotal":0,"ratingScore":0,"tags":{},"RelationScore":"2.2222222222222223E-02"},{"id":"455","name":"ドラえもん のび太の創世日記","type":2,"ratingTotal":230,"ratingScore":7.3,"tags":{},"RelationScore":"2.1428571428571432E-02"},{"id":"823","name":"名探偵コナン 瞳の中の暗殺者","type":2,"ratingTotal":2053,"ratingScore":7.2,"tags":{},"RelationScore":"2.1428571428571432E-02"},{"id":"22566","name":"ゴッドイーター 禁忌を破る者","type":1,"ratingTotal":2,"ratingScore":6,"tags":{},"RelationScore":"2.1428571428571432E-02"}]