[{"id":"236103","name":"踏切時間","type":2,"ratingTotal":850,"ratingScore":6.8,"tags":{},"RelationScore":"1E-01"},{"id":"195943","name":"苺時間","type":1,"ratingTotal":0,"ratingScore":0,"tags":{},"RelationScore":"5E-02"},{"id":"1760","name":"イヴの時間","type":2,"ratingTotal":2018,"ratingScore":7.9,"tags":{},"RelationScore":"4E-02"},{"id":"82085","name":"学校の時間","type":1,"ratingTotal":4,"ratingScore":6,"tags":{},"RelationScore":"4E-02"},{"id":"110283","name":"幸せの時間","type":1,"ratingTotal":4,"ratingScore":7.5,"tags":{},"RelationScore":"4E-02"},{"id":"233510","name":"おやつの時間","type":1,"ratingTotal":51,"ratingScore":7.2,"tags":{},"RelationScore":"3.333333333333334E-02"},{"id":"1595","name":"ふわふわ時間","type":3,"ratingTotal":316,"ratingScore":7.6,"tags":{},"RelationScore":"3.333333333333334E-02"},{"id":"3487","name":"足りない時間","type":1,"ratingTotal":38,"ratingScore":7.3,"tags":{},"RelationScore":"3.333333333333334E-02"},{"id":"57603","name":"しずくの時間","type":4,"ratingTotal":36,"ratingScore":7.3,"tags":{"Android":1,"IOS":1,"雫的日常":1,"手游":1,"Live2D":1,"Mobile":1},"RelationScore":"3.333333333333334E-02"},{"id":"106059","name":"こどもの時間","type":2,"ratingTotal":61,"ratingScore":5.9,"tags":{},"RelationScore":"3.333333333333334E-02"}]